{"version":3,"kind":"Article","sha256":"4560792c8b4afe23074a211a9474b79811599c6fcab92bfe98eaa1d7c1a3780d","slug":"notebook-hub-guide","location":"/notebook-hub-guide.md","dependencies":[],"frontmatter":{"title":"Notebook Hub Setup Guide","content_includes_title":false,"exports":[{"format":"md","filename":"notebook-hub-guide.md","url":"/notebook-hub-guide-d773a20e82ad4a92cebaecf559485e37.md"}]},"mdast":{"type":"root","children":[{"type":"block","children":[{"type":"paragraph","position":{"start":{"line":3,"column":1},"end":{"line":3,"column":1}},"children":[{"type":"text","value":"A complete guide to publishing Jupyter Notebooks online as a central hub, accessible from any device.","position":{"start":{"line":3,"column":1},"end":{"line":3,"column":1}},"key":"JlpWjiSjCV"}],"key":"ZU6uDQjcpk"},{"type":"thematicBreak","position":{"start":{"line":5,"column":1},"end":{"line":5,"column":1}},"key":"koAHoCisLM"},{"type":"heading","depth":2,"position":{"start":{"line":7,"column":1},"end":{"line":7,"column":1}},"children":[{"type":"text","value":"Overview","position":{"start":{"line":7,"column":1},"end":{"line":7,"column":1}},"key":"Sq7zLniavB"}],"identifier":"overview","label":"Overview","html_id":"overview","implicit":true,"key":"P4EP9A1gZW"},{"type":"list","ordered":false,"spread":false,"position":{"start":{"line":9,"column":1},"end":{"line":13,"column":1}},"children":[{"type":"listItem","spread":true,"position":{"start":{"line":9,"column":1},"end":{"line":9,"column":1}},"children":[{"type":"paragraph","children":[{"type":"strong","position":{"start":{"line":9,"column":1},"end":{"line":9,"column":1}},"children":[{"type":"text","value":"Tool:","position":{"start":{"line":9,"column":1},"end":{"line":9,"column":1}},"key":"Q7VJ7Vwcdm"}],"key":"Y7cT48bzSB"},{"type":"text","value":" JupyterBook v2 (MyST)","position":{"start":{"line":9,"column":1},"end":{"line":9,"column":1}},"key":"CbDf2EHwPT"}],"key":"YiQIahrk51"}],"key":"wzIdQp5Xcg"},{"type":"listItem","spread":true,"position":{"start":{"line":10,"column":1},"end":{"line":10,"column":1}},"children":[{"type":"paragraph","children":[{"type":"strong","position":{"start":{"line":10,"column":1},"end":{"line":10,"column":1}},"children":[{"type":"text","value":"Source repo:","position":{"start":{"line":10,"column":1},"end":{"line":10,"column":1}},"key":"NFYvK5EAlo"}],"key":"g6AOqGNpSl"},{"type":"text","value":" GitHub (private or public)","position":{"start":{"line":10,"column":1},"end":{"line":10,"column":1}},"key":"SnQLLTT8sU"}],"key":"NXU1HmlnBD"}],"key":"mJcCqwcjR8"},{"type":"listItem","spread":true,"position":{"start":{"line":11,"column":1},"end":{"line":11,"column":1}},"children":[{"type":"paragraph","children":[{"type":"strong","position":{"start":{"line":11,"column":1},"end":{"line":11,"column":1}},"children":[{"type":"text","value":"Hosting:","position":{"start":{"line":11,"column":1},"end":{"line":11,"column":1}},"key":"LTsGnZQbsp"}],"key":"fTsIH3lV7W"},{"type":"text","value":" GitHub Pages (free)","position":{"start":{"line":11,"column":1},"end":{"line":11,"column":1}},"key":"OiFZUXtRiN"}],"key":"vlB1BkvwqA"}],"key":"buJ8vsgXY0"},{"type":"listItem","spread":true,"position":{"start":{"line":12,"column":1},"end":{"line":13,"column":1}},"children":[{"type":"paragraph","children":[{"type":"strong","position":{"start":{"line":12,"column":1},"end":{"line":12,"column":1}},"children":[{"type":"text","value":"Live URL:","position":{"start":{"line":12,"column":1},"end":{"line":12,"column":1}},"key":"KkwKCvj7aZ"}],"key":"GrjQwWHxdT"},{"type":"text","value":" ","position":{"start":{"line":12,"column":1},"end":{"line":12,"column":1}},"key":"we8OqDJzM1"},{"type":"inlineCode","value":"https://liamli123.github.io/notebooks/","position":{"start":{"line":12,"column":1},"end":{"line":12,"column":1}},"key":"HnmPzG7Rok"}],"key":"XK3Gkw92qS"}],"key":"iZWmaRYk5D"}],"key":"xAoh1xkO1O"},{"type":"thematicBreak","position":{"start":{"line":14,"column":1},"end":{"line":14,"column":1}},"key":"tDwRXNiU6n"},{"type":"heading","depth":2,"position":{"start":{"line":16,"column":1},"end":{"line":16,"column":1}},"children":[{"type":"text","value":"One-Time Setup","position":{"start":{"line":16,"column":1},"end":{"line":16,"column":1}},"key":"WriySyn5YG"}],"identifier":"one-time-setup","label":"One-Time Setup","html_id":"one-time-setup","implicit":true,"key":"lbv2c2ZtHM"},{"type":"heading","depth":3,"position":{"start":{"line":18,"column":1},"end":{"line":18,"column":1}},"children":[{"type":"text","value":"1. Prerequisites","position":{"start":{"line":18,"column":1},"end":{"line":18,"column":1}},"key":"eJXnmWiE0e"}],"identifier":"id-1-prerequisites","label":"1. Prerequisites","html_id":"id-1-prerequisites","implicit":true,"key":"rGU3QVRtKM"},{"type":"paragraph","position":{"start":{"line":20,"column":1},"end":{"line":20,"column":1}},"children":[{"type":"text","value":"Make sure these are installed:","position":{"start":{"line":20,"column":1},"end":{"line":20,"column":1}},"key":"MswXzd0TYr"}],"key":"zngLKIwolF"},{"type":"code","lang":"powershell","value":"pip install jupyter-book ghp-import\nnode --version   # must be >= 18\nnpm --version    # must be >= 8.6","position":{"start":{"line":22,"column":1},"end":{"line":26,"column":1}},"key":"KodL9y6YII"},{"type":"heading","depth":3,"position":{"start":{"line":28,"column":1},"end":{"line":28,"column":1}},"children":[{"type":"text","value":"2. Create the Hub Folder","position":{"start":{"line":28,"column":1},"end":{"line":28,"column":1}},"key":"cKVQqKmty7"}],"identifier":"id-2-create-the-hub-folder","label":"2. Create the Hub Folder","html_id":"id-2-create-the-hub-folder","implicit":true,"key":"q4TRF0ZIhS"},{"type":"blockquote","position":{"start":{"line":30,"column":1},"end":{"line":30,"column":1}},"children":[{"type":"paragraph","position":{"start":{"line":30,"column":1},"end":{"line":30,"column":1}},"children":[{"type":"text","value":"⚠️ Do NOT create this inside Google Drive or OneDrive — npm will fail.","position":{"start":{"line":30,"column":1},"end":{"line":30,"column":1}},"key":"nSsil4gnLX"}],"key":"Sq5HiFoztq"}],"key":"JfSytoQ4hv"},{"type":"code","lang":"powershell","value":"cd C:\\Users\\YourName\\Documents   # or any local drive (E:, C:, etc.)\nmkdir my-hub\ncd my-hub\njupyter-book init\n# When asked to run jupyter-book start → Yes (to download theme)\n# Then Ctrl+C to stop the local server","position":{"start":{"line":32,"column":1},"end":{"line":39,"column":1}},"key":"nrrbwMW2C0"},{"type":"heading","depth":3,"position":{"start":{"line":41,"column":1},"end":{"line":41,"column":1}},"children":[{"type":"text","value":"3. Add Your Notebooks","position":{"start":{"line":41,"column":1},"end":{"line":41,"column":1}},"key":"ON2arcQ8fI"}],"identifier":"id-3-add-your-notebooks","label":"3. Add Your Notebooks","html_id":"id-3-add-your-notebooks","implicit":true,"key":"UYkbsWECmi"},{"type":"paragraph","position":{"start":{"line":43,"column":1},"end":{"line":43,"column":1}},"children":[{"type":"text","value":"Simply drag and drop ","position":{"start":{"line":43,"column":1},"end":{"line":43,"column":1}},"key":"nkdIjNptsu"},{"type":"inlineCode","value":".ipynb","position":{"start":{"line":43,"column":1},"end":{"line":43,"column":1}},"key":"qseij2qFn9"},{"type":"text","value":" files into the ","position":{"start":{"line":43,"column":1},"end":{"line":43,"column":1}},"key":"le6UATFDZZ"},{"type":"inlineCode","value":"my-hub","position":{"start":{"line":43,"column":1},"end":{"line":43,"column":1}},"key":"J0L7fj5t4s"},{"type":"text","value":" folder using File Explorer.","position":{"start":{"line":43,"column":1},"end":{"line":43,"column":1}},"key":"VfNTC6Hw3A"}],"key":"ZkbSO3dR1Y"},{"type":"blockquote","position":{"start":{"line":45,"column":1},"end":{"line":45,"column":1}},"children":[{"type":"paragraph","position":{"start":{"line":45,"column":1},"end":{"line":45,"column":1}},"children":[{"type":"strong","position":{"start":{"line":45,"column":1},"end":{"line":45,"column":1}},"children":[{"type":"text","value":"Tip:","position":{"start":{"line":45,"column":1},"end":{"line":45,"column":1}},"key":"TWUOGAzb6d"}],"key":"VaRCxxfp7y"},{"type":"text","value":" Always run notebooks in Jupyter first and save with output before dropping them in. This ensures students see full results on the site.","position":{"start":{"line":45,"column":1},"end":{"line":45,"column":1}},"key":"exqW4257Ui"}],"key":"JyfYTqLuq9"}],"key":"mqJCVGzJKF"},{"type":"heading","depth":3,"position":{"start":{"line":47,"column":1},"end":{"line":47,"column":1}},"children":[{"type":"text","value":"4. Build the Site Locally (First Time)","position":{"start":{"line":47,"column":1},"end":{"line":47,"column":1}},"key":"PhTMUarfg1"}],"identifier":"id-4-build-the-site-locally-first-time","label":"4. Build the Site Locally (First Time)","html_id":"id-4-build-the-site-locally-first-time","implicit":true,"key":"KuXHhBzC2v"},{"type":"code","lang":"powershell","value":"cd E:\\Websites\\Notebooks\\my-hub   # your hub folder\njupyter-book build","position":{"start":{"line":49,"column":1},"end":{"line":52,"column":1}},"key":"DuCDPwXrrK"},{"type":"heading","depth":3,"position":{"start":{"line":54,"column":1},"end":{"line":54,"column":1}},"children":[{"type":"text","value":"5. Set Up GitHub Pages Deployment","position":{"start":{"line":54,"column":1},"end":{"line":54,"column":1}},"key":"OO2SPO1B90"}],"identifier":"id-5-set-up-github-pages-deployment","label":"5. Set Up GitHub Pages Deployment","html_id":"id-5-set-up-github-pages-deployment","implicit":true,"key":"dfFLbv658s"},{"type":"paragraph","position":{"start":{"line":56,"column":1},"end":{"line":56,"column":1}},"children":[{"type":"text","value":"Make sure your hub folder is a Git repo connected to GitHub, then run:","position":{"start":{"line":56,"column":1},"end":{"line":56,"column":1}},"key":"kUGT0PJ4ql"}],"key":"KMUptszk81"},{"type":"code","lang":"powershell","value":"jupyter-book init --gh-pages\n# Branch: master\n# Action name: deploy.yml (press Enter)","position":{"start":{"line":58,"column":1},"end":{"line":62,"column":1}},"key":"z0lpXWm7oE"},{"type":"paragraph","position":{"start":{"line":64,"column":1},"end":{"line":64,"column":1}},"children":[{"type":"text","value":"This creates a ","position":{"start":{"line":64,"column":1},"end":{"line":64,"column":1}},"key":"HLKoaLL4Ep"},{"type":"inlineCode","value":".github/workflows/deploy.yml","position":{"start":{"line":64,"column":1},"end":{"line":64,"column":1}},"key":"TfHQz1hAXj"},{"type":"text","value":" file automatically.","position":{"start":{"line":64,"column":1},"end":{"line":64,"column":1}},"key":"X0eN9MaFb7"}],"key":"FKamdocHO4"},{"type":"heading","depth":3,"position":{"start":{"line":66,"column":1},"end":{"line":66,"column":1}},"children":[{"type":"text","value":"6. Create GitHub Repo and Push","position":{"start":{"line":66,"column":1},"end":{"line":66,"column":1}},"key":"y1Ka0b34TB"}],"identifier":"id-6-create-github-repo-and-push","label":"6. Create GitHub Repo and Push","html_id":"id-6-create-github-repo-and-push","implicit":true,"key":"WBPFnO8ENk"},{"type":"paragraph","position":{"start":{"line":68,"column":1},"end":{"line":68,"column":1}},"children":[{"type":"text","value":"Go to ","position":{"start":{"line":68,"column":1},"end":{"line":68,"column":1}},"key":"MJEpDsxzLA"},{"type":"link","url":"https://github.com","position":{"start":{"line":68,"column":1},"end":{"line":68,"column":1}},"children":[{"type":"text","value":"github.com","position":{"start":{"line":68,"column":1},"end":{"line":68,"column":1}},"key":"CJC0V3nh4o"}],"urlSource":"https://github.com","key":"qbeRrIGMq0"},{"type":"text","value":" → ","position":{"start":{"line":68,"column":1},"end":{"line":68,"column":1}},"key":"H28lKgQZoN"},{"type":"strong","position":{"start":{"line":68,"column":1},"end":{"line":68,"column":1}},"children":[{"type":"text","value":"New Repository","position":{"start":{"line":68,"column":1},"end":{"line":68,"column":1}},"key":"LzAwN5tkPi"}],"key":"XqJwYUBdow"},{"type":"text","value":" → name it ","position":{"start":{"line":68,"column":1},"end":{"line":68,"column":1}},"key":"t3cUQhvrau"},{"type":"inlineCode","value":"notebooks","position":{"start":{"line":68,"column":1},"end":{"line":68,"column":1}},"key":"Ywg7SgjO1n"},{"type":"text","value":" → ","position":{"start":{"line":68,"column":1},"end":{"line":68,"column":1}},"key":"ST8al2RZ40"},{"type":"strong","position":{"start":{"line":68,"column":1},"end":{"line":68,"column":1}},"children":[{"type":"text","value":"Public","position":{"start":{"line":68,"column":1},"end":{"line":68,"column":1}},"key":"KqqENG1AZ0"}],"key":"Ish7Hw4xWG"},{"type":"text","value":" → Create.","position":{"start":{"line":68,"column":1},"end":{"line":68,"column":1}},"key":"un75BDBBOe"}],"key":"TFSKtj0tKS"},{"type":"paragraph","position":{"start":{"line":70,"column":1},"end":{"line":70,"column":1}},"children":[{"type":"text","value":"Then run:","position":{"start":{"line":70,"column":1},"end":{"line":70,"column":1}},"key":"KeKVXlgKK2"}],"key":"U0enem4C87"},{"type":"code","lang":"powershell","value":"cd E:\\Websites\\Notebooks\\my-hub\ngit init\ngit add .\ngit commit -m \"first commit\"\ngit remote add origin https://github.com/liamli123/notebooks.git\ngit push -u origin master","position":{"start":{"line":72,"column":1},"end":{"line":79,"column":1}},"key":"W8NSSpbdqo"},{"type":"blockquote","position":{"start":{"line":81,"column":1},"end":{"line":81,"column":1}},"children":[{"type":"paragraph","position":{"start":{"line":81,"column":1},"end":{"line":81,"column":1}},"children":[{"type":"text","value":"Note: Use ","position":{"start":{"line":81,"column":1},"end":{"line":81,"column":1}},"key":"b90iKaxLkz"},{"type":"inlineCode","value":"master","position":{"start":{"line":81,"column":1},"end":{"line":81,"column":1}},"key":"jNudKgggdU"},{"type":"text","value":" not ","position":{"start":{"line":81,"column":1},"end":{"line":81,"column":1}},"key":"pRasbT1DwK"},{"type":"inlineCode","value":"main","position":{"start":{"line":81,"column":1},"end":{"line":81,"column":1}},"key":"fadEXwDAl9"},{"type":"text","value":" — this machine defaults to ","position":{"start":{"line":81,"column":1},"end":{"line":81,"column":1}},"key":"ku2W7dFO6Q"},{"type":"inlineCode","value":"master","position":{"start":{"line":81,"column":1},"end":{"line":81,"column":1}},"key":"glRPSsEu7q"},{"type":"text","value":".","position":{"start":{"line":81,"column":1},"end":{"line":81,"column":1}},"key":"kb5miFn6j8"}],"key":"AwNBCblTYZ"}],"key":"lRrkWdMtpD"},{"type":"heading","depth":3,"position":{"start":{"line":83,"column":1},"end":{"line":83,"column":1}},"children":[{"type":"text","value":"7. Enable GitHub Pages","position":{"start":{"line":83,"column":1},"end":{"line":83,"column":1}},"key":"GspWEXYzje"}],"identifier":"id-7-enable-github-pages","label":"7. Enable GitHub Pages","html_id":"id-7-enable-github-pages","implicit":true,"key":"fhhTqqtgiN"},{"type":"paragraph","position":{"start":{"line":85,"column":1},"end":{"line":85,"column":1}},"children":[{"type":"text","value":"Go to ","position":{"start":{"line":85,"column":1},"end":{"line":85,"column":1}},"key":"unNeQtIvNf"},{"type":"strong","position":{"start":{"line":85,"column":1},"end":{"line":85,"column":1}},"children":[{"type":"link","url":"http://github.com/liamli123/notebooks","position":{"start":{"line":85,"column":1},"end":{"line":85,"column":1}},"children":[{"type":"text","value":"github​.com​/liamli123​/notebooks","position":{"start":{"line":85,"column":1},"end":{"line":85,"column":1}},"key":"zfWxsUNNHu"}],"urlSource":"http://github.com/liamli123/notebooks","error":true,"key":"McLNWu7pAE"}],"key":"neDyQiMMpG"},{"type":"text","value":" → ","position":{"start":{"line":85,"column":1},"end":{"line":85,"column":1}},"key":"ZWauaHjwoe"},{"type":"strong","position":{"start":{"line":85,"column":1},"end":{"line":85,"column":1}},"children":[{"type":"text","value":"Settings","position":{"start":{"line":85,"column":1},"end":{"line":85,"column":1}},"key":"ecWsIfhJhs"}],"key":"G9nN72TCpX"},{"type":"text","value":" → ","position":{"start":{"line":85,"column":1},"end":{"line":85,"column":1}},"key":"UwsP4SOWmi"},{"type":"strong","position":{"start":{"line":85,"column":1},"end":{"line":85,"column":1}},"children":[{"type":"text","value":"Pages","position":{"start":{"line":85,"column":1},"end":{"line":85,"column":1}},"key":"m1SIHznxQq"}],"key":"RZz5UhwNG9"},{"type":"text","value":" → under ","position":{"start":{"line":85,"column":1},"end":{"line":85,"column":1}},"key":"IU9ZBUKTVL"},{"type":"strong","position":{"start":{"line":85,"column":1},"end":{"line":85,"column":1}},"children":[{"type":"text","value":"Source","position":{"start":{"line":85,"column":1},"end":{"line":85,"column":1}},"key":"tJLeQNyWsg"}],"key":"Kwytq5sfPa"},{"type":"text","value":" select ","position":{"start":{"line":85,"column":1},"end":{"line":85,"column":1}},"key":"MsJlkLmU6H"},{"type":"strong","position":{"start":{"line":85,"column":1},"end":{"line":85,"column":1}},"children":[{"type":"text","value":"GitHub Actions","position":{"start":{"line":85,"column":1},"end":{"line":85,"column":1}},"key":"sJDFKR9NFv"}],"key":"wOC5ieQBv9"},{"type":"text","value":" → Save.","position":{"start":{"line":85,"column":1},"end":{"line":85,"column":1}},"key":"dDiwXXfaZJ"}],"key":"kRbTB9I5wG"},{"type":"paragraph","position":{"start":{"line":87,"column":1},"end":{"line":87,"column":1}},"children":[{"type":"text","value":"Wait 2-3 minutes. Your site is live at:","position":{"start":{"line":87,"column":1},"end":{"line":87,"column":1}},"key":"SRByDZuPDe"}],"key":"kg6hiuj0Xe"},{"type":"code","lang":"","value":"https://liamli123.github.io/notebooks/","position":{"start":{"line":89,"column":1},"end":{"line":91,"column":1}},"key":"IKxzlPvNAf"},{"type":"thematicBreak","position":{"start":{"line":93,"column":1},"end":{"line":93,"column":1}},"key":"MVoXWuPAB0"},{"type":"heading","depth":2,"position":{"start":{"line":95,"column":1},"end":{"line":95,"column":1}},"children":[{"type":"text","value":"Adding New Notebooks (Regular Workflow)","position":{"start":{"line":95,"column":1},"end":{"line":95,"column":1}},"key":"fojNmdQi3Y"}],"identifier":"adding-new-notebooks-regular-workflow","label":"Adding New Notebooks (Regular Workflow)","html_id":"adding-new-notebooks-regular-workflow","implicit":true,"key":"LbzEOgooMf"},{"type":"paragraph","position":{"start":{"line":97,"column":1},"end":{"line":97,"column":1}},"children":[{"type":"text","value":"Every time you finish a notebook and want to publish it:","position":{"start":{"line":97,"column":1},"end":{"line":97,"column":1}},"key":"mhNkLAGjfU"}],"key":"uhySkikhO3"},{"type":"paragraph","position":{"start":{"line":99,"column":1},"end":{"line":99,"column":1}},"children":[{"type":"strong","position":{"start":{"line":99,"column":1},"end":{"line":99,"column":1}},"children":[{"type":"text","value":"Step 1:","position":{"start":{"line":99,"column":1},"end":{"line":99,"column":1}},"key":"WPOBBUUT9Z"}],"key":"LUErzPjix7"},{"type":"text","value":" Drop the ","position":{"start":{"line":99,"column":1},"end":{"line":99,"column":1}},"key":"cEyIEJM3lx"},{"type":"inlineCode","value":".ipynb","position":{"start":{"line":99,"column":1},"end":{"line":99,"column":1}},"key":"gQZtKU9kZO"},{"type":"text","value":" file into ","position":{"start":{"line":99,"column":1},"end":{"line":99,"column":1}},"key":"amr7Lkht1V"},{"type":"inlineCode","value":"E:\\Websites\\Notebooks\\my-hub\\","position":{"start":{"line":99,"column":1},"end":{"line":99,"column":1}},"key":"N3rGZklEim"}],"key":"mSHon8td36"},{"type":"paragraph","position":{"start":{"line":101,"column":1},"end":{"line":101,"column":1}},"children":[{"type":"strong","position":{"start":{"line":101,"column":1},"end":{"line":101,"column":1}},"children":[{"type":"text","value":"Step 2:","position":{"start":{"line":101,"column":1},"end":{"line":101,"column":1}},"key":"mqzdUGLqoB"}],"key":"J1cv5kySAa"},{"type":"text","value":" Run:","position":{"start":{"line":101,"column":1},"end":{"line":101,"column":1}},"key":"BJVAMrmm5d"}],"key":"uwWPdZUKfE"},{"type":"code","lang":"powershell","value":"cd E:\\Websites\\Notebooks\\my-hub\njupyter-book build\ngit add .\ngit commit -m \"added new notebook\"\ngit push origin master","position":{"start":{"line":103,"column":1},"end":{"line":109,"column":1}},"key":"l3OfaDuijy"},{"type":"paragraph","position":{"start":{"line":111,"column":1},"end":{"line":111,"column":1}},"children":[{"type":"strong","position":{"start":{"line":111,"column":1},"end":{"line":111,"column":1}},"children":[{"type":"text","value":"Step 3:","position":{"start":{"line":111,"column":1},"end":{"line":111,"column":1}},"key":"Zw2VDegvpj"}],"key":"GqRyMgYA68"},{"type":"text","value":" Wait 2-3 minutes → site auto-updates.","position":{"start":{"line":111,"column":1},"end":{"line":111,"column":1}},"key":"WazkiWxS1K"}],"key":"WsN8FM7ohK"},{"type":"thematicBreak","position":{"start":{"line":113,"column":1},"end":{"line":113,"column":1}},"key":"ooNkmk0ahy"},{"type":"heading","depth":2,"position":{"start":{"line":115,"column":1},"end":{"line":115,"column":1}},"children":[{"type":"text","value":"Adding Notebooks from Another Computer","position":{"start":{"line":115,"column":1},"end":{"line":115,"column":1}},"key":"QjsDgLjrim"}],"identifier":"adding-notebooks-from-another-computer","label":"Adding Notebooks from Another Computer","html_id":"adding-notebooks-from-another-computer","implicit":true,"key":"n0WPUPvOK8"},{"type":"code","lang":"powershell","value":"# First time on a new computer — clone the repo\ngit clone https://github.com/liamli123/notebooks.git\ncd notebooks\n\n# Drop in new notebooks, then:\njupyter-book build\ngit add .\ngit commit -m \"added new notebook\"\ngit push origin master","position":{"start":{"line":117,"column":1},"end":{"line":127,"column":1}},"key":"qgNRS7dCOq"},{"type":"thematicBreak","position":{"start":{"line":129,"column":1},"end":{"line":129,"column":1}},"key":"UnNrimccgV"},{"type":"heading","depth":2,"position":{"start":{"line":131,"column":1},"end":{"line":131,"column":1}},"children":[{"type":"text","value":"Folder Structure","position":{"start":{"line":131,"column":1},"end":{"line":131,"column":1}},"key":"WDlOIgI1UI"}],"identifier":"folder-structure","label":"Folder Structure","html_id":"folder-structure","implicit":true,"key":"pnUb4skoMf"},{"type":"code","lang":"","value":"my-hub/\n├── .github/\n│   └── workflows/\n│       └── deploy.yml       ← GitHub Action (auto-deploy)\n├── myst.yml                 ← hub config\n├── Assignment1.ipynb\n├── Assignment2.ipynb\n├── ML_Deep_Dive.ipynb\n└── _build/                  ← auto-generated, do not edit","position":{"start":{"line":133,"column":1},"end":{"line":143,"column":1}},"key":"nspSjBWv0p"},{"type":"thematicBreak","position":{"start":{"line":145,"column":1},"end":{"line":145,"column":1}},"key":"OCnJaD3zDr"},{"type":"heading","depth":2,"position":{"start":{"line":147,"column":1},"end":{"line":147,"column":1}},"children":[{"type":"text","value":"Key Notes","position":{"start":{"line":147,"column":1},"end":{"line":147,"column":1}},"key":"vhAwWn3sop"}],"identifier":"key-notes","label":"Key Notes","html_id":"key-notes","implicit":true,"key":"JWIzrH193B"},{"type":"list","ordered":false,"spread":false,"position":{"start":{"line":149,"column":1},"end":{"line":156,"column":1}},"children":[{"type":"listItem","spread":true,"position":{"start":{"line":149,"column":1},"end":{"line":149,"column":1}},"children":[{"type":"paragraph","children":[{"type":"strong","position":{"start":{"line":149,"column":1},"end":{"line":149,"column":1}},"children":[{"type":"text","value":"Never put the hub folder inside Google Drive/OneDrive","position":{"start":{"line":149,"column":1},"end":{"line":149,"column":1}},"key":"qJjBxmtYlr"}],"key":"cxfL3uOaIF"},{"type":"text","value":" — npm breaks","position":{"start":{"line":149,"column":1},"end":{"line":149,"column":1}},"key":"AI6ceoCmQw"}],"key":"QCVEfdMocs"}],"key":"NRFHVDZbjS"},{"type":"listItem","spread":true,"position":{"start":{"line":150,"column":1},"end":{"line":150,"column":1}},"children":[{"type":"paragraph","children":[{"type":"strong","position":{"start":{"line":150,"column":1},"end":{"line":150,"column":1}},"children":[{"type":"text","value":"Always run notebooks before dropping them in","position":{"start":{"line":150,"column":1},"end":{"line":150,"column":1}},"key":"FHlLClGZri"}],"key":"M0NShZqMW1"},{"type":"text","value":" — so output is saved","position":{"start":{"line":150,"column":1},"end":{"line":150,"column":1}},"key":"K4YYGYAjql"}],"key":"wsHv8fSzVR"}],"key":"Rz4Pygfcvx"},{"type":"listItem","spread":true,"position":{"start":{"line":151,"column":1},"end":{"line":151,"column":1}},"children":[{"type":"paragraph","children":[{"type":"strong","position":{"start":{"line":151,"column":1},"end":{"line":151,"column":1}},"children":[{"type":"inlineCode","value":"_build/","position":{"start":{"line":151,"column":1},"end":{"line":151,"column":1}},"key":"PRcpGRXOZk"},{"type":"text","value":" is auto-generated","position":{"start":{"line":151,"column":1},"end":{"line":151,"column":1}},"key":"vsvVPYFsMe"}],"key":"lxIjYw5nyp"},{"type":"text","value":" — no need to touch it","position":{"start":{"line":151,"column":1},"end":{"line":151,"column":1}},"key":"Q94RxHObfQ"}],"key":"HuhMFfh7JX"}],"key":"iBYhkMdPxJ"},{"type":"listItem","spread":true,"position":{"start":{"line":152,"column":1},"end":{"line":152,"column":1}},"children":[{"type":"paragraph","children":[{"type":"strong","position":{"start":{"line":152,"column":1},"end":{"line":152,"column":1}},"children":[{"type":"text","value":"GitHub repo must be Public","position":{"start":{"line":152,"column":1},"end":{"line":152,"column":1}},"key":"Q3GTxDxkmw"}],"key":"dkzz3dwwhd"},{"type":"text","value":" for free GitHub Pages hosting","position":{"start":{"line":152,"column":1},"end":{"line":152,"column":1}},"key":"ikgxbvpXNc"}],"key":"gw7xa1cbkR"}],"key":"zpHqwrTW9e"},{"type":"listItem","spread":true,"position":{"start":{"line":153,"column":1},"end":{"line":153,"column":1}},"children":[{"type":"paragraph","children":[{"type":"strong","position":{"start":{"line":153,"column":1},"end":{"line":153,"column":1}},"children":[{"type":"text","value":"Branch name is ","position":{"start":{"line":153,"column":1},"end":{"line":153,"column":1}},"key":"TM6ydmSpXK"},{"type":"inlineCode","value":"master","position":{"start":{"line":153,"column":1},"end":{"line":153,"column":1}},"key":"BgwLSodMy5"}],"key":"g5g1tLgXxg"},{"type":"text","value":" on this machine (not ","position":{"start":{"line":153,"column":1},"end":{"line":153,"column":1}},"key":"r7DkyYvxjz"},{"type":"inlineCode","value":"main","position":{"start":{"line":153,"column":1},"end":{"line":153,"column":1}},"key":"A0ty4wEGJV"},{"type":"text","value":")","position":{"start":{"line":153,"column":1},"end":{"line":153,"column":1}},"key":"jLxBPQjWMN"}],"key":"bGte43Hp4H"}],"key":"WDIBKunfq9"},{"type":"listItem","spread":true,"position":{"start":{"line":154,"column":1},"end":{"line":154,"column":1}},"children":[{"type":"paragraph","children":[{"type":"strong","position":{"start":{"line":154,"column":1},"end":{"line":154,"column":1}},"children":[{"type":"text","value":"Vercel does NOT work","position":{"start":{"line":154,"column":1},"end":{"line":154,"column":1}},"key":"qNb3Xtwwff"}],"key":"G2CfosBfcz"},{"type":"text","value":" with MyST v2 as a static site — GitHub Pages is the correct solution","position":{"start":{"line":154,"column":1},"end":{"line":154,"column":1}},"key":"D4lKoKrEBP"}],"key":"t92jjTGsdJ"}],"key":"s2BeeTYimk"},{"type":"listItem","spread":true,"position":{"start":{"line":155,"column":1},"end":{"line":156,"column":1}},"children":[{"type":"paragraph","children":[{"type":"strong","position":{"start":{"line":155,"column":1},"end":{"line":155,"column":1}},"children":[{"type":"inlineCode","value":"myst","position":{"start":{"line":155,"column":1},"end":{"line":155,"column":1}},"key":"UAStt3vOM0"},{"type":"text","value":" command is not in PATH","position":{"start":{"line":155,"column":1},"end":{"line":155,"column":1}},"key":"QnVxxIgArX"}],"key":"T29LFBPtvs"},{"type":"text","value":" — use ","position":{"start":{"line":155,"column":1},"end":{"line":155,"column":1}},"key":"JbsyUuhXP9"},{"type":"inlineCode","value":"jupyter-book","position":{"start":{"line":155,"column":1},"end":{"line":155,"column":1}},"key":"x2mEIg65Xw"},{"type":"text","value":" instead","position":{"start":{"line":155,"column":1},"end":{"line":155,"column":1}},"key":"Jrae7zOgcZ"}],"key":"U3Lvfgr2Mx"}],"key":"qXOjLJUuky"}],"key":"Daxzj5OsFo"},{"type":"thematicBreak","position":{"start":{"line":157,"column":1},"end":{"line":157,"column":1}},"key":"hmBAdvt4I0"},{"type":"heading","depth":2,"position":{"start":{"line":159,"column":1},"end":{"line":159,"column":1}},"children":[{"type":"text","value":"Troubleshooting","position":{"start":{"line":159,"column":1},"end":{"line":159,"column":1}},"key":"oltquQmjnt"}],"identifier":"troubleshooting","label":"Troubleshooting","html_id":"troubleshooting","implicit":true,"key":"sqoxEa3414"},{"type":"table","position":{"start":{"line":161,"column":1},"end":{"line":168,"column":1}},"children":[{"type":"tableRow","position":{"start":{"line":161,"column":1},"end":{"line":161,"column":1}},"children":[{"type":"tableCell","header":true,"position":{"start":{"line":161,"column":1},"end":{"line":161,"column":1}},"children":[{"type":"text","value":"Problem","position":{"start":{"line":161,"column":1},"end":{"line":161,"column":1}},"key":"iS7XevfDYR"}],"key":"S28x7hj3hv"},{"type":"tableCell","header":true,"position":{"start":{"line":161,"column":1},"end":{"line":161,"column":1}},"children":[{"type":"text","value":"Fix","position":{"start":{"line":161,"column":1},"end":{"line":161,"column":1}},"key":"gzuSf2aaX2"}],"key":"Og4hnQEfCs"}],"key":"wRerSrynJu"},{"type":"tableRow","position":{"start":{"line":163,"column":1},"end":{"line":163,"column":1}},"children":[{"type":"tableCell","position":{"start":{"line":163,"column":1},"end":{"line":163,"column":1}},"children":[{"type":"inlineCode","value":"npm TAR_ENTRY_ERROR","position":{"start":{"line":163,"column":1},"end":{"line":163,"column":1}},"key":"TfGertgG4A"}],"key":"liDj25V47f"},{"type":"tableCell","position":{"start":{"line":163,"column":1},"end":{"line":163,"column":1}},"children":[{"type":"text","value":"Hub folder is inside Google Drive — move to local drive","position":{"start":{"line":163,"column":1},"end":{"line":163,"column":1}},"key":"iEwZda1KPC"}],"key":"E9BhcOQNhx"}],"key":"zrG7H41T9O"},{"type":"tableRow","position":{"start":{"line":164,"column":1},"end":{"line":164,"column":1}},"children":[{"type":"tableCell","position":{"start":{"line":164,"column":1},"end":{"line":164,"column":1}},"children":[{"type":"inlineCode","value":"myst: not recognized","position":{"start":{"line":164,"column":1},"end":{"line":164,"column":1}},"key":"wFmdqK9wPl"}],"key":"WnfE5CWeq4"},{"type":"tableCell","position":{"start":{"line":164,"column":1},"end":{"line":164,"column":1}},"children":[{"type":"text","value":"Use ","position":{"start":{"line":164,"column":1},"end":{"line":164,"column":1}},"key":"l9teR4aU0T"},{"type":"inlineCode","value":"jupyter-book","position":{"start":{"line":164,"column":1},"end":{"line":164,"column":1}},"key":"eQf3zqkaJn"},{"type":"text","value":" instead of ","position":{"start":{"line":164,"column":1},"end":{"line":164,"column":1}},"key":"Emaurgp2ov"},{"type":"inlineCode","value":"myst","position":{"start":{"line":164,"column":1},"end":{"line":164,"column":1}},"key":"V5cJsJWZ6b"}],"key":"Mmj3jBNFcN"}],"key":"jyopceTsI3"},{"type":"tableRow","position":{"start":{"line":165,"column":1},"end":{"line":165,"column":1}},"children":[{"type":"tableCell","position":{"start":{"line":165,"column":1},"end":{"line":165,"column":1}},"children":[{"type":"inlineCode","value":"src refspec main does not match","position":{"start":{"line":165,"column":1},"end":{"line":165,"column":1}},"key":"b3IOJQeuP9"}],"key":"waqAwJBbfB"},{"type":"tableCell","position":{"start":{"line":165,"column":1},"end":{"line":165,"column":1}},"children":[{"type":"text","value":"Use ","position":{"start":{"line":165,"column":1},"end":{"line":165,"column":1}},"key":"SAq4XGLjbY"},{"type":"inlineCode","value":"git push origin master","position":{"start":{"line":165,"column":1},"end":{"line":165,"column":1}},"key":"cmCZWluoYu"},{"type":"text","value":" not ","position":{"start":{"line":165,"column":1},"end":{"line":165,"column":1}},"key":"ed97oMvBPq"},{"type":"inlineCode","value":"main","position":{"start":{"line":165,"column":1},"end":{"line":165,"column":1}},"key":"COFgashSY2"}],"key":"Zy1LoXiCIq"}],"key":"tnR5aAPr6h"},{"type":"tableRow","position":{"start":{"line":166,"column":1},"end":{"line":166,"column":1}},"children":[{"type":"tableCell","position":{"start":{"line":166,"column":1},"end":{"line":166,"column":1}},"children":[{"type":"text","value":"GitHub Pages 404","position":{"start":{"line":166,"column":1},"end":{"line":166,"column":1}},"key":"XMjcBeB7G0"}],"key":"G4NkHOFts6"},{"type":"tableCell","position":{"start":{"line":166,"column":1},"end":{"line":166,"column":1}},"children":[{"type":"text","value":"Make sure Source is set to ","position":{"start":{"line":166,"column":1},"end":{"line":166,"column":1}},"key":"BkFJMsl41I"},{"type":"strong","position":{"start":{"line":166,"column":1},"end":{"line":166,"column":1}},"children":[{"type":"text","value":"GitHub Actions","position":{"start":{"line":166,"column":1},"end":{"line":166,"column":1}},"key":"P6EutBnIPv"}],"key":"ynpgzrhDzW"},{"type":"text","value":" not “Deploy from branch”","position":{"start":{"line":166,"column":1},"end":{"line":166,"column":1}},"key":"ZfU6MY4YSi"}],"key":"bqmcrHPiUb"}],"key":"WI4i0isE8U"},{"type":"tableRow","position":{"start":{"line":167,"column":1},"end":{"line":167,"column":1}},"children":[{"type":"tableCell","position":{"start":{"line":167,"column":1},"end":{"line":167,"column":1}},"children":[{"type":"text","value":"Vercel 404","position":{"start":{"line":167,"column":1},"end":{"line":167,"column":1}},"key":"jSKVjb5q0I"}],"key":"WSc8nCWsK7"},{"type":"tableCell","position":{"start":{"line":167,"column":1},"end":{"line":167,"column":1}},"children":[{"type":"text","value":"Don’t use Vercel — use GitHub Pages instead","position":{"start":{"line":167,"column":1},"end":{"line":167,"column":1}},"key":"yuvkueUxo8"}],"key":"sfmNARdDER"}],"key":"sZ8ItnsFPy"},{"type":"tableRow","position":{"start":{"line":168,"column":1},"end":{"line":168,"column":1}},"children":[{"type":"tableCell","position":{"start":{"line":168,"column":1},"end":{"line":168,"column":1}},"children":[{"type":"text","value":"Notebooks show no output","position":{"start":{"line":168,"column":1},"end":{"line":168,"column":1}},"key":"J78L2juufx"}],"key":"SvDwz7i4Rd"},{"type":"tableCell","position":{"start":{"line":168,"column":1},"end":{"line":168,"column":1}},"children":[{"type":"text","value":"Re-run notebook in Jupyter, save, then re-add to hub","position":{"start":{"line":168,"column":1},"end":{"line":168,"column":1}},"key":"RIan284om7"}],"key":"Sudep4Bu9J"}],"key":"lJt6cD3P7G"}],"key":"d4VF0i1K8o"},{"type":"thematicBreak","position":{"start":{"line":170,"column":1},"end":{"line":170,"column":1}},"key":"qOzdHW1bN5"},{"type":"heading","depth":2,"position":{"start":{"line":172,"column":1},"end":{"line":172,"column":1}},"children":[{"type":"text","value":"Useful Links","position":{"start":{"line":172,"column":1},"end":{"line":172,"column":1}},"key":"LJQ18zZbRD"}],"identifier":"useful-links","label":"Useful Links","html_id":"useful-links","implicit":true,"key":"whpq9hoDo2"},{"type":"list","ordered":false,"spread":false,"position":{"start":{"line":174,"column":1},"end":{"line":176,"column":1}},"children":[{"type":"listItem","spread":true,"position":{"start":{"line":174,"column":1},"end":{"line":174,"column":1}},"children":[{"type":"paragraph","children":[{"type":"text","value":"Live site: ","position":{"start":{"line":174,"column":1},"end":{"line":174,"column":1}},"key":"jk4ldUznAi"},{"type":"link","url":"https://liamli123.github.io/notebooks/","position":{"start":{"line":174,"column":1},"end":{"line":174,"column":1}},"children":[{"type":"text","value":"https://​liamli123​.github​.io​/notebooks/","position":{"start":{"line":174,"column":1},"end":{"line":174,"column":1}},"key":"eNtD1RqTiC"}],"urlSource":"https://liamli123.github.io/notebooks/","key":"dkRTJx3U4E"}],"key":"zrAFNjSZZE"}],"key":"KPjJGazwJr"},{"type":"listItem","spread":true,"position":{"start":{"line":175,"column":1},"end":{"line":175,"column":1}},"children":[{"type":"paragraph","children":[{"type":"text","value":"GitHub repo: ","position":{"start":{"line":175,"column":1},"end":{"line":175,"column":1}},"key":"m6BEDe4Vbj"},{"type":"link","url":"https://github.com/liamli123/notebooks","position":{"start":{"line":175,"column":1},"end":{"line":175,"column":1}},"children":[{"type":"text","value":"https://​github​.com​/liamli123​/notebooks","position":{"start":{"line":175,"column":1},"end":{"line":175,"column":1}},"key":"iFAQcCRuLA"}],"urlSource":"https://github.com/liamli123/notebooks","error":true,"key":"SRlf3OvViz"}],"key":"POs8gunGFa"}],"key":"DbBh4iF5GF"},{"type":"listItem","spread":true,"position":{"start":{"line":176,"column":1},"end":{"line":176,"column":1}},"children":[{"type":"paragraph","children":[{"type":"text","value":"GitHub Actions log: ","position":{"start":{"line":176,"column":1},"end":{"line":176,"column":1}},"key":"Z6UMQshuvI"},{"type":"link","url":"https://github.com/liamli123/notebooks/actions","position":{"start":{"line":176,"column":1},"end":{"line":176,"column":1}},"children":[{"type":"text","value":"https://​github​.com​/liamli123​/notebooks​/actions","position":{"start":{"line":176,"column":1},"end":{"line":176,"column":1}},"key":"TTCtNCTOrd"}],"urlSource":"https://github.com/liamli123/notebooks/actions","error":true,"key":"rdcj0KqWty"}],"key":"nPtRaC99yb"}],"key":"Ssx2NSkj9c"}],"key":"pSboYinInl"}],"key":"WmBdyuZ1i9"}],"key":"iZtCIdRNa1"},"references":{"cite":{"order":[],"data":{}}}}